magic_folder/__init__.py
magic_folder/__main__.py
magic_folder/_coverage.py
magic_folder/_endpoint_parser.py
magic_folder/_schema.py
magic_folder/_version.py
magic_folder/api_cli.py
magic_folder/cli.py
magic_folder/client.py
magic_folder/common.py
magic_folder/config.py
magic_folder/downloader.py
magic_folder/endpoints.py
magic_folder/initialize.py
magic_folder/invite.py
magic_folder/join.py
magic_folder/list.py
magic_folder/magic_file.py
magic_folder/magic_folder.py
magic_folder/magicpath.py
magic_folder/migrate.py
magic_folder/participants.py
magic_folder/pid.py
magic_folder/scanner.py
magic_folder/service.py
magic_folder/show_config.py
magic_folder/snapshot.py
magic_folder/status.py
magic_folder/tahoe_client.py
magic_folder/uploader.py
magic_folder/web.py
magic_folder/test/__init__.py
magic_folder/test/agentutil.py
magic_folder/test/common.py
magic_folder/test/eliotutil.py
magic_folder/test/fixtures.py
magic_folder/test/matchers.py
magic_folder/test/strategies.py
magic_folder/test/test_api_cli.py
magic_folder/test/test_cli.py
magic_folder/test/test_client.py
magic_folder/test/test_common.py
magic_folder/test/test_config.py
magic_folder/test/test_download.py
magic_folder/test/test_eliotutil.py
magic_folder/test/test_endpoints.py
magic_folder/test/test_foo.py
magic_folder/test/test_invite.py
magic_folder/test/test_local_snapshot.py
magic_folder/test/test_magic_file.py
magic_folder/test/test_magic_folder_service.py
magic_folder/test/test_magicpath.py
magic_folder/test/test_participants.py
magic_folder/test/test_pid.py
magic_folder/test/test_scanner.py
magic_folder/test/test_schema.py
magic_folder/test/test_service.py
magic_folder/test/test_snapshot.py
magic_folder/test/test_status.py
magic_folder/test/test_strategies.py
magic_folder/test/test_tahoe_client.py
magic_folder/test/test_testing.py
magic_folder/test/test_upload.py
magic_folder/test/test_util_attrs_zope.py
magic_folder/test/test_util_database.py
magic_folder/test/test_util_file.py
magic_folder-24.3.0.dist-info/COPYING.GPL
magic_folder-24.3.0.dist-info/COPYING.TGPPL.rst
magic_folder-24.3.0.dist-info/METADATA
magic_folder-24.3.0.dist-info/WHEEL
magic_folder-24.3.0.dist-info/entry_points.txt
magic_folder-24.3.0.dist-info/top_level.txt
magic_folder-24.3.0.dist-info/RECORD
