Metadata-Version: 2.1
Name: magic-folder
Version: 24.3.0
Summary: Tahoe-LAFS-based file synchronization
Home-page: https://github.com/LeastAuthority/magic-folder/
Author: the Tahoe-LAFS developers, the Magic-Folder developers
Author-email: tahoe-dev@tahoe-lafs.org
License: GNU GPL
Classifier: Development Status :: 5 - Production/Stable
Classifier: Environment :: Console
Classifier: Environment :: Web Environment
Classifier: License :: OSI Approved :: GNU General Public License (GPL)
Classifier: License :: DFSG approved
Classifier: License :: Other/Proprietary License
Classifier: Intended Audience :: Developers
Classifier: Intended Audience :: End Users/Desktop
Classifier: Intended Audience :: System Administrators
Classifier: Operating System :: Microsoft
Classifier: Operating System :: Microsoft :: Windows
Classifier: Operating System :: Unix
Classifier: Operating System :: POSIX :: Linux
Classifier: Operating System :: POSIX
Classifier: Operating System :: MacOS :: MacOS X
Classifier: Operating System :: OS Independent
Classifier: Natural Language :: English
Classifier: Programming Language :: Python
Classifier: Topic :: Utilities
Classifier: Topic :: System :: Systems Administration
Classifier: Topic :: System :: Filesystems
Classifier: Topic :: System :: Distributed Computing
Classifier: Topic :: Software Development :: Libraries
Classifier: Topic :: System :: Archiving :: Mirroring
Classifier: Topic :: System :: Archiving
License-File: COPYING.GPL
License-File: COPYING.TGPPL.rst
Requires-Dist: zope.interface !=3.6.3,!=3.6.4,>=3.6.0
Requires-Dist: humanize >=1.0.0
Requires-Dist: eliot
Requires-Dist: attrs
Requires-Dist: autobahn >=19.5.2
Requires-Dist: hyperlink
Requires-Dist: tahoe-lafs >=1.18.0
Requires-Dist: treq
Requires-Dist: appdirs
Requires-Dist: pyutil >=3.3.0
Requires-Dist: cryptography >=2.6
Requires-Dist: klein >=20.6.0
Requires-Dist: psutil >=5.8.0
Requires-Dist: filelock >=3.8.0
Requires-Dist: cbor2 !=5.6.0
Provides-Extra: build
Requires-Dist: setuptools-scm >=6.4.0 ; extra == 'build'
Requires-Dist: dulwich >=0.20.30 ; extra == 'build'
Requires-Dist: twine >=3.7.1 ; extra == 'build'
Requires-Dist: towncrier >=21.3.0 ; extra == 'build'
Requires-Dist: readme-renderer >=32.0 ; extra == 'build'
Requires-Dist: wheel >=0.37.1 ; extra == 'build'
Requires-Dist: gpg >=1.10.0 ; extra == 'build'
Provides-Extra: test
Requires-Dist: flake8 ==3.9.2 ; extra == 'test'
Requires-Dist: flake8-future-import ; extra == 'test'
Requires-Dist: coverage ; extra == 'test'
Requires-Dist: tox ; extra == 'test'
Requires-Dist: mock ; extra == 'test'
Requires-Dist: pytest ; extra == 'test'
Requires-Dist: colorama ; extra == 'test'
Requires-Dist: pytest-twisted ; extra == 'test'
Requires-Dist: hypothesis >=3.6.1 ; extra == 'test'
Requires-Dist: towncrier >=21.3.0 ; extra == 'test'
Requires-Dist: testtools ; extra == 'test'
Requires-Dist: fixtures ; extra == 'test'
Requires-Dist: psutil ; extra == 'test'
Requires-Dist: magic-wormhole-mailbox-server ; extra == 'test'
